wsocket.py
WSocket-2.1.0.data/scripts/wsocket.py
WSocket-2.1.0.dist-info/LICENSE
WSocket-2.1.0.dist-info/METADATA
WSocket-2.1.0.dist-info/WHEEL
WSocket-2.1.0.dist-info/top_level.txt
WSocket-2.1.0.dist-info/RECORD
